centuri_course/Answers.py
centuri_course/__init__.py
centuri_course/anatomy.py
centuri_course/rain.py
centuri_course/transform-latex.py
centuri_course/utils.py
centuri_course-2024.1.3.dist-info/LICENSE
centuri_course-2024.1.3.dist-info/METADATA
centuri_course-2024.1.3.dist-info/WHEEL
centuri_course-2024.1.3.dist-info/top_level.txt
centuri_course-2024.1.3.dist-info/RECORD
